MANIFEST.in
setup.cfg
setup.py
SFMT/SFMT-alti.h
SFMT/SFMT-common.h
SFMT/SFMT-neon.h
SFMT/SFMT-params.h
SFMT/SFMT-params11213.h
SFMT/SFMT-params1279.h
SFMT/SFMT-params132049.h
SFMT/SFMT-params19937.h
SFMT/SFMT-params216091.h
SFMT/SFMT-params2281.h
SFMT/SFMT-params4253.h
SFMT/SFMT-params44497.h
SFMT/SFMT-params607.h
SFMT/SFMT-params86243.h
SFMT/SFMT-sse2-msc.h
SFMT/SFMT-sse2.h
SFMT/SFMT.c
SFMT/SFMT.h
SFMT/jump/SFMT-jump.h
SFMT/jump/calc-characteristic.h
pysfmt/pysfmt.pxd
pysfmt/pysfmt.pyx
pysfmt.egg-info/PKG-INFO
pysfmt.egg-info/SOURCES.txt
pysfmt.egg-info/dependency_links.txt
pysfmt.egg-info/requires.txt
pysfmt.egg-info/top_level.txt